confdict/__init__.py
confdict/confdict.py
confdict-0.0.1.dist-info/LICENSE.md
confdict-0.0.1.dist-info/WHEEL
confdict-0.0.1.dist-info/METADATA
confdict-0.0.1.dist-info/RECORD
