Metadata-Version: 2.1
Name: confdict
Version: 0.0.1
Summary: A dictionary with nested access, interpolation and fallback features. It is primarily meant to be used for storing configurations of programs.
Home-page: None
Author: Mehmet Can Ozdemir
Author-email: mefu.ozd@gmail.com
Requires-Python: >=3.4,<4.0
Classifier: License :: OSI Approved :: MIT License
Classifier: Programming Language :: Python :: 3
Classifier: Programming Language :: Python :: 3.4
Classifier: Programming Language :: Python :: 3.5
Classifier: Programming Language :: Python :: 3.6
Classifier: Programming Language :: Python :: 3.7
